meshed/__init__.py
meshed/base.py
meshed/caching.py
meshed/components.py
meshed/composition.py
meshed/dag.py
meshed/itools.py
meshed/makers.py
meshed/slabs.py
meshed/tools.py
meshed/util.py
meshed/viz.py
meshed/examples/__init__.py
meshed/examples/online_marketing.py
meshed/examples/price_elasticity.py
meshed/examples/vaccine_vs_no_vaccine.py
meshed/ext/__init__.py
meshed/ext/gk.py
meshed/ext/gk_tests.py
meshed/scrap/__init__.py
meshed/scrap/annotations_to_meshes.py
meshed/scrap/cached_dag.py
meshed/scrap/collapse_and_expand.py
meshed/scrap/conversion.py
meshed/scrap/dask_graph_language.py
meshed/scrap/flow_control_script.py
meshed/scrap/gk_with_networkx.py
meshed/scrap/gui_interaction.py
meshed/scrap/misc_utils.py
meshed/scrap/reactive_scope.py
meshed/scrap/wrapping_dags.py
meshed/tests/__init__.py
meshed/tests/objects_for_testing.py
meshed/tests/test_base.py
meshed/tests/test_caching.py
meshed/tests/test_ch_funcs.py
meshed/tests/test_components.py
meshed/tests/test_composition.py
meshed/tests/test_dag.py
meshed/tests/test_dag_2.py
meshed/tests/test_dag_defaults.py
meshed/tests/test_dag_variadics.py
meshed/tests/test_getitem.py
meshed/tests/test_itools.py
meshed/tests/test_makers.py
meshed/tests/test_meshed_tools.py
meshed/tests/test_util.py
meshed/tests/utils_for_testing.py
meshed-0.1.165.dist-info/LICENSE
meshed-0.1.165.dist-info/METADATA
meshed-0.1.165.dist-info/WHEEL
meshed-0.1.165.dist-info/top_level.txt
meshed-0.1.165.dist-info/RECORD
