Metadata-Version: 2.1
Name: meshed
Version: 0.1.165
Summary: Link functions up into callable objects
Home-page: https://github.com/i2mint/meshed
License: mit
Keywords: dag,graph,network
Platform: any
License-File: LICENSE
Requires-Dist: i2
